poga/__init__.py
poga/capi/poga.hpp
poga/capi/poga_cmodule.cpp
poga/capi/poga_manager.cpp
poga/capi/poga_manager.hpp
poga/deps/yoga/BitUtils.h
poga/deps/yoga/CompactValue.h
poga/deps/yoga/event/event.cpp
poga/deps/yoga/event/event.h
poga/deps/yoga/internal/experiments-inl.h
poga/deps/yoga/internal/experiments.cpp
poga/deps/yoga/internal/experiments.h
poga/deps/yoga/log.cpp
poga/deps/yoga/log.h
poga/deps/yoga/Utils.cpp
poga/deps/yoga/Utils.h
poga/deps/yoga/YGConfig.cpp
poga/deps/yoga/YGConfig.h
poga/deps/yoga/YGEnums.cpp
poga/deps/yoga/YGEnums.h
poga/deps/yoga/YGFloatOptional.h
poga/deps/yoga/YGLayout.cpp
poga/deps/yoga/YGLayout.h
poga/deps/yoga/YGMacros.h
poga/deps/yoga/YGNode.cpp
poga/deps/yoga/YGNode.h
poga/deps/yoga/YGNodePrint.cpp
poga/deps/yoga/YGNodePrint.h
poga/deps/yoga/YGStyle.cpp
poga/deps/yoga/YGStyle.h
poga/deps/yoga/YGValue.cpp
poga/deps/yoga/YGValue.h
poga/deps/yoga/Yoga-internal.h
poga/deps/yoga/Yoga.cpp
poga/deps/yoga/Yoga.h
poga/libpoga_capi.cp38-win_amd64.pyd
poga/libpoga_capi.pyi
poga/poga_layout.py
poga/poga_types.py
poga/poga_view.py
poga/py.typed
poga-0.1.19.dist-info/entry_points.txt
poga-0.1.19.dist-info/LICENSE
poga-0.1.19.dist-info/METADATA
poga-0.1.19.dist-info/WHEEL
poga-0.1.19.dist-info/RECORD
