Metadata-Version: 2.1
Name: poga
Version: 0.1.19
License-File: LICENSE
Requires-Dist: pybind11>=2.2.0
